endpoints/__init__.py
endpoints/detections.py
endpoints/images.py
endpoints/map_features.py
endpoints/organizations.py
endpoints/sequences.py
endpoints/vector_tiles.py
mapiry-1.0.0.dist-info/licenses/LICENSE
mapiry-1.0.0.dist-info/METADATA
mapiry-1.0.0.dist-info/WHEEL
mapiry-1.0.0.dist-info/top_level.txt
mapiry-1.0.0.dist-info/RECORD
