Metadata-Version: 2.4
Name: mapiry
Version: 1.0.0
Summary: A comprehensive Python SDK for Mapillary API v4
Author-email: tikisan <s2501082@sendai-nct.jp>
License: MIT
Project-URL: Homepage, https://github.com/tikipiya/Mapiry
Project-URL: Bug Tracker, https://github.com/tikipiya/Mapiry/issues
Project-URL: Documentation, https://github.com/tikipiya/Mapiry/blob/main/README.md
Project-URL: Source, https://github.com/tikipiya/Mapiry
Keywords: mapillary,api,sdk,street-view,imagery,computer-vision,gis
Classifier: Development Status :: 5 - Production/Stable
Classifier: Intended Audience :: Developers
Classifier: License :: OSI Approved :: MIT License
Classifier: Operating System :: OS Independent
Classifier: Programming Language :: Python :: 3
Classifier: Programming Language :: Python :: 3.7
Classifier: Programming Language :: Python :: 3.8
Classifier: Programming Language :: Python :: 3.9
Classifier: Programming Language :: Python :: 3.10
Classifier: Programming Language :: Python :: 3.11
Classifier: Programming Language :: Python :: 3.12
Classifier: Topic :: Software Development :: Libraries :: Python Modules
Classifier: Topic :: Scientific/Engineering :: GIS
Classifier: Topic :: Internet :: WWW/HTTP :: Dynamic Content
Requires-Python: >=3.7
License-File: LICENSE
Requires-Dist: requests>=2.25.0
Requires-Dist: urllib3>=1.26.0
Requires-Dist: python-dateutil>=2.8.0
Requires-Dist: typing-extensions>=4.0.0
Requires-Dist: pydantic>=1.8.0
Dynamic: license-file
